comparator_operations/__init__.py
comparator_operations/core.py
comparator_operations/operations.py
comparator_operations/services.py
comparator_operations/utils.py
data_comparator/__init__.py
io_operations/__init__.py
io_operations/io_utils.py
logger/__init__.py
logger/bcolors.py
logger/logger.py
logger/tabular_log.py
wai_datacomparator-0.1.0b1.dist-info/METADATA
wai_datacomparator-0.1.0b1.dist-info/WHEEL
wai_datacomparator-0.1.0b1.dist-info/top_level.txt
wai_datacomparator-0.1.0b1.dist-info/RECORD
