Metadata-Version: 2.1
Name: wai-datacomparator
Version: 0.1.0b1
Summary: Data Comparator: A Python package for comparing data from two files. The service reads a configuration file that specifies the details of the comparison operation, such as the logger configurations, old file and new file for the comparison along with the file type, Primary key information. Easy to use and highly flexible, Data Comparator simplifies the process of merging data.
Home-page: https://bitbucket.org/wilsonai/wai_misc/src/wai-pkg-001
Author: RAJ PATEL
Author-email: rajp@aliteprojects.in
Maintainer: RAJ PATEL
Maintainer-email: rajp@aliteprojects.in
Classifier: Development Status :: 2 - Pre-Alpha
Classifier: Intended Audience :: Developers
Classifier: Topic :: Software Development :: Build Tools
Classifier: License :: OSI Approved :: MIT License
Classifier: Programming Language :: Python :: 3
Classifier: Programming Language :: Python :: 3.10
Requires-Python: ==3.10.*
Requires-Dist: pandas
Requires-Dist: tabulate
